Timer.v
/*
Author: sanket nyayadhish
date : 28 august 2018
Implementation of an artificial neuron in Verilog
*/

module Timer(
              input Clk,
              input Input,
              input Enable,
              output[31:0] Count
              );
              
              
wire Clk,Input,Enable;
reg p_start = 0;
reg [31:0] Count =0;
              always@(Input or Clk)
              begin
              if (Enable == 1)
              begin
              Count = 32'b0;
              p_start = 0;
              end
              else
              begin
              if (Input == 1)
              begin
              //Count   = 32'd0;
              p_start = 1;
              end
              end
              end
              
             always@(posedge(Clk) or p_start)
             begin
             if (p_start == 1)
             Count = Count + 1'b1;
             end  
              
              endmodule

Function.v
/*
Author: sanket nyayadhish
date : 28 gust 2018
Implementation of an artificial neuron in Verilog
*/

module Function (
                  input[31:0] In,
                  input [3:0]Weight,
                  output [31:0]Result
                  );
                  
                  
wire[31:0] In;
wire [3:0] Weight;
reg [31:0] Result;
                  
                  always@(*)
                  begin
                  
                   Result = (In*Weight)/4;
                  
                  end
                  
                  endmodule

Inhibit.v
/*
Author: sanket nyayadhish
date : 28 august 2018
Implementation of an artificial neuron in Verilog
*/

module Inhibit(
                input Clk,
                input p_s,
                output Enable,
                output Pulse
                );
                
                
wire Clk,p_s;
reg Pulse,Enable;
reg [31:0] cont;

                always@(p_s or Clk)
                begin
                Pulse = p_s;
                end
                
                always@(posedge p_s)
                begin
                //$display("HELLO");
                cont   = 0;
                Enable = 1;
                end
                always@(posedge Clk)
                begin
                if ( p_s == 0 )
                begin
                 //$display("HELLO1");
                cont = cont + 1;
                end
                if (cont > 3)
                begin
                 //$display("HELLO2");
                Enable = 0;
                end
                end     
                
                
 endmodule

A_C.v
/*
Author: sanket nyayadhish
date : 28 gust 2018
Implementation of an artificial neuron in Verilog
*/

module A_C(
             input[31:0] D1,
             input[31:0] D2,
             input[31:0] D3,
             output Ins);
            
wire D1,D2,D3;
reg Ins;

            always@(*)
            begin
            if ( D1 + D2 + D3 > 9)
            begin
            Ins = 1;
            end
            else
            Ins = 0;
            end
            
            
endmodule

Neuron.v
/*
Author: sanket nyayadhish
date : 28 gust 2018
Implementation of an artificial neuron in Verilog
*/

`include "A_C.v"
`include "Inhibit.v"
`include "Function.v"
`include "Timer.v"

module Neuron(
              input Clk
              );


wire Clk;
reg DE1,DE2,DE3;
reg [3:0] W1,W2,W3;
wire En,Out;
wire OUT_PULSE;
wire [31:0] C1,C2,C3,R1,R2,R3;

A_C      ADD_COMP(R1,R2,R3,Out);
Inhibit  Inhibit1(Clk,Out,En,OUT_PULSE);
Function F1(C1,W1,R1);
Function F2(C2,W2,R2);
Function F3(C3,W3,R3);
Timer    T1(Clk,DE1,En,C1);
Timer    T2(Clk,DE2,En,C2);
Timer    T3(Clk,DE3,En,C3);

 
 
endmodule

Test_neuron.v
/*
Author: sanket nyayadhish
date : 28 august 2018
Implementation of an artificial neuron in Verilog
*/
`include"Neuron.v"
`timescale 1ns/1ns
          module Test_neuron();

          reg Clk;
          Neuron N(Clk);

          always 
          begin
          #5 Clk =~ Clk;
          end


         initial 
         begin
         $dumpfile("Test_neuron.vcd");
         $dumpvars(0,N);
        // $monitor("  %d %d %d %d %d %d %d",$time,N.R1,N.R2,N.R3,N.Out,N.OUT_PULSE,N.En,N.Inhibit1.cont);
         Clk = 0;
         N.DE1 = 1;
         N.DE2 = 1;
         N.DE3 = 1;
           N.W1 = 4'b1000;
           N.W2 = 4'b0100;
           N.W3 = 4'b1111;
           #100
         N.W1 = 4'b111;
         N.W2 = 4'b0011;
         N.W3 = 4'b0111;
         #100
        N.W1 = 4'b0000;
        N.W2 = 4'b0000;
        N.W3 = 4'b0000;
        #100
         N.W1 = 4'b111;
         N.W2 = 4'b0011;
         N.W3 = 4'b0111;
         
        #500 $finish ;
         end     
        endmodule

Test_neuron.vcd
$date
	Fri Aug 31 21:34:35 2018
$end
$version
	Icarus Verilog
$end
$timescale
	1ns
$end
$scope module Test_neuron $end
$scope module N $end
$var wire 1 ! Clk $end
$var wire 32 " R3 [31:0] $end
$var wire 32 # R2 [31:0] $end
$var wire 32 $ R1 [31:0] $end
$var wire 1 % Out $end
$var wire 1 & OUT_PULSE $end
$var wire 1 ' En $end
$var wire 32 ( C3 [31:0] $end
$var wire 32 ) C2 [31:0] $end
$var wire 32 * C1 [31:0] $end
$var reg 1 + DE1 $end
$var reg 1 , DE2 $end
$var reg 1 - DE3 $end
$var reg 4 . W1 [3:0] $end
$var reg 4 / W2 [3:0] $end
$var reg 4 0 W3 [3:0] $end
$scope module ADD_COMP $end
$var wire 32 1 D3 [31:0] $end
$var wire 32 2 D2 [31:0] $end
$var wire 32 3 D1 [31:0] $end
$var reg 1 % Ins $end
$upscope $end
$scope module F1 $end
$var wire 4 4 Weight [3:0] $end
$var wire 32 5 In [31:0] $end
$var reg 32 6 Result [31:0] $end
$upscope $end
$scope module F2 $end
$var wire 4 7 Weight [3:0] $end
$var wire 32 8 In [31:0] $end
$var reg 32 9 Result [31:0] $end
$upscope $end
$scope module F3 $end
$var wire 4 : Weight [3:0] $end
$var wire 32 ; In [31:0] $end
$var reg 32 < Result [31:0] $end
$upscope $end
$scope module Inhibit1 $end
$var wire 1 ! Clk $end
$var wire 1 % p_s $end
$var reg 1 ' Enable $end
$var reg 1 & Pulse $end
$var reg 32 = cont [31:0] $end
$upscope $end
$scope module T1 $end
$var wire 1 ! Clk $end
$var wire 1 ' Enable $end
$var wire 1 + Input $end
$var reg 32 > Count [31:0] $end
$var reg 1 ? p_start $end
$upscope $end
$scope module T2 $end
$var wire 1 ! Clk $end
$var wire 1 ' Enable $end
$var wire 1 , Input $end
$var reg 32 @ Count [31:0] $end
$var reg 1 A p_start $end
$upscope $end
$scope module T3 $end
$var wire 1 ! Clk $end
$var wire 1 ' Enable $end
$var wire 1 - Input $end
$var reg 32 B Count [31:0] $end
$var reg 1 C p_start $end
$upscope $end
$upscope $end
$upscope $end
$enddefinitions $end
#0
$dumpvars
1C
b1 B
1A
b1 @
1?
b1 >
bx =
b11 <
b1 ;
b1111 :
b1 9
b1 8
b100 7
b10 6
b1 5
b1000 4
b10 3
b1 2
b11 1
b1111 0
b100 /
b1000 .
1-
1,
1+
b1 *
b1 )
b1 (
x'
0&
0%
b10 $
b1 #
b11 "
0!
$end
#5
1'
b0 =
1&
1%
b100 $
b100 3
b100 6
b10 #
b10 2
b10 9
b111 "
b111 1
b111 <
b10 *
b10 5
b10 >
b10 )
b10 8
b10 @
b10 (
b10 ;
b10 B
1!
#10
0&
0%
b0 $
b0 3
b0 6
b0 #
b0 2
b0 9
b0 "
b0 1
b0 <
0?
b0 *
b0 5
b0 >
0A
b0 )
b0 8
b0 @
0C
b0 (
b0 ;
b0 B
0!
#15
b1 =
1!
#20
0!
#25
b10 =
1!
#30
0!
#35
b11 =
1!
#40
0!
#45
0'
b100 =
1!
#50
b10 $
b10 3
b10 6
b1 #
b1 2
b1 9
b11 "
b11 1
b11 <
b1 *
b1 5
b1 >
b1 )
b1 8
b1 @
b1 (
b1 ;
b1 B
1?
1A
1C
0!
#55
1'
1&
1%
b100 $
b100 3
b100 6
b10 #
b10 2
b10 9
b111 "
b111 1
b111 <
b0 =
b10 *
b10 5
b10 >
b10 )
b10 8
b10 @
b10 (
b10 ;
b10 B
1!
#60
0&
0%
b0 $
b0 3
b0 6
b0 #
b0 2
b0 9
b0 "
b0 1
b0 <
0?
b0 *
b0 5
b0 >
0A
b0 )
b0 8
b0 @
0C
b0 (
b0 ;
b0 B
0!
#65
b1 =
1!
#70
0!
#75
b10 =
1!
#80
0!
#85
b11 =
1!
#90
0!
#95
0'
b100 =
1!
#100
b1 $
b1 3
b1 6
b1 "
b1 1
b1 <
b1 *
b1 5
b1 >
b1 )
b1 8
b1 @
b1 (
b1 ;
b1 B
1?
1A
1C
0!
b111 0
b111 :
b11 /
b11 7
b111 .
b111 4
#105
b11 $
b11 3
b11 6
b1 #
b1 2
b1 9
b11 "
b11 1
b11 <
b101 =
b10 *
b10 5
b10 >
b10 )
b10 8
b10 @
b10 (
b10 ;
b10 B
1!
#110
0!
#115
1'
1&
1%
b101 $
b101 3
b101 6
b10 #
b10 2
b10 9
b101 "
b101 1
b101 <
b0 =
b11 *
b11 5
b11 >
b11 )
b11 8
b11 @
b11 (
b11 ;
b11 B
1!
#120
0&
0%
b0 $
b0 3
b0 6
b0 #
b0 2
b0 9
b0 "
b0 1
b0 <
0?
b0 *
b0 5
b0 >
0A
b0 )
b0 8
b0 @
0C
b0 (
b0 ;
b0 B
0!
#125
b1 =
1!
#130
0!
#135
b10 =
1!
#140
0!
#145
b11 =
1!
#150
0!
#155
0'
b100 =
1!
#160
b1 $
b1 3
b1 6
b1 "
b1 1
b1 <
b1 *
b1 5
b1 >
b1 )
b1 8
b1 @
b1 (
b1 ;
b1 B
1?
1A
1C
0!
#165
b11 $
b11 3
b11 6
b1 #
b1 2
b1 9
b11 "
b11 1
b11 <
b101 =
b10 *
b10 5
b10 >
b10 )
b10 8
b10 @
b10 (
b10 ;
b10 B
1!
#170
0!
#175
1'
1&
1%
b101 $
b101 3
b101 6
b10 #
b10 2
b10 9
b101 "
b101 1
b101 <
b0 =
b11 *
b11 5
b11 >
b11 )
b11 8
b11 @
b11 (
b11 ;
b11 B
1!
#180
0&
0%
b0 $
b0 3
b0 6
b0 #
b0 2
b0 9
b0 "
b0 1
b0 <
0?
b0 *
b0 5
b0 >
0A
b0 )
b0 8
b0 @
0C
b0 (
b0 ;
b0 B
0!
#185
b1 =
1!
#190
0!
#195
b10 =
1!
#200
0!
b0 0
b0 :
b0 /
b0 7
b0 .
b0 4
#205
b11 =
1!
#210
0!
#215
0'
b100 =
1!
#220
b1 *
b1 5
b1 >
b1 )
b1 8
b1 @
b1 (
b1 ;
b1 B
1?
1A
1C
0!
#225
b101 =
b10 *
b10 5
b10 >
b10 )
b10 8
b10 @
b10 (
b10 ;
b10 B
1!
#230
0!
#235
b110 =
b11 *
b11 5
b11 >
b11 )
b11 8
b11 @
b11 (
b11 ;
b11 B
1!
#240
0!
#245
b111 =
b100 *
b100 5
b100 >
b100 )
b100 8
b100 @
b100 (
b100 ;
b100 B
1!
#250
0!
#255
b1000 =
b101 *
b101 5
b101 >
b101 )
b101 8
b101 @
b101 (
b101 ;
b101 B
1!
#260
0!
#265
b1001 =
b110 *
b110 5
b110 >
b110 )
b110 8
b110 @
b110 (
b110 ;
b110 B
1!
#270
0!
#275
b1010 =
b111 *
b111 5
b111 >
b111 )
b111 8
b111 @
b111 (
b111 ;
b111 B
1!
#280
0!
#285
b1011 =
b1000 *
b1000 5
b1000 >
b1000 )
b1000 8
b1000 @
b1000 (
b1000 ;
b1000 B
1!
#290
0!
#295
b1100 =
b1001 *
b1001 5
b1001 >
b1001 )
b1001 8
b1001 @
b1001 (
b1001 ;
b1001 B
1!
#300
1'
b0 =
1&
1%
b1111 "
b1111 1
b1111 <
b110 #
b110 2
b110 9
b1111 $
b1111 3
b1111 6
0!
b111 0
b111 :
b11 /
b11 7
b111 .
b111 4
#305
0&
0%
b0 $
b0 3
b0 6
b0 #
b0 2
b0 9
b0 "
b0 1
b0 <
0?
b0 *
b0 5
b0 >
0A
b0 )
b0 8
b0 @
0C
b0 (
b0 ;
b0 B
1!
#310
0!
#315
b1 =
1!
#320
0!
#325
b10 =
1!
#330
0!
#335
b11 =
1!
#340
0!
#345
0'
b100 =
1!
#350
b1 $
b1 3
b1 6
b1 "
b1 1
b1 <
b1 *
b1 5
b1 >
b1 )
b1 8
b1 @
b1 (
b1 ;
b1 B
1?
1A
1C
0!
#355
b11 $
b11 3
b11 6
b1 #
b1 2
b1 9
b11 "
b11 1
b11 <
b101 =
b10 *
b10 5
b10 >
b10 )
b10 8
b10 @
b10 (
b10 ;
b10 B
1!
#360
0!
#365
1'
1&
1%
b101 $
b101 3
b101 6
b10 #
b10 2
b10 9
b101 "
b101 1
b101 <
b0 =
b11 *
b11 5
b11 >
b11 )
b11 8
b11 @
b11 (
b11 ;
b11 B
1!
#370
0&
0%
b0 $
b0 3
b0 6
b0 #
b0 2
b0 9
b0 "
b0 1
b0 <
0?
b0 *
b0 5
b0 >
0A
b0 )
b0 8
b0 @
0C
b0 (
b0 ;
b0 B
0!
#375
b1 =
1!
#380
0!
#385
b10 =
1!
#390
0!
#395
b11 =
1!
#400
0!
#405
0'
b100 =
1!
#410
b1 $
b1 3
b1 6
b1 "
b1 1
b1 <
b1 *
b1 5
b1 >
b1 )
b1 8
b1 @
b1 (
b1 ;
b1 B
1?
1A
1C
0!
#415
b11 $
b11 3
b11 6
b1 #
b1 2
b1 9
b11 "
b11 1
b11 <
b101 =
b10 *
b10 5
b10 >
b10 )
b10 8
b10 @
b10 (
b10 ;
b10 B
1!
#420
0!
#425
1'
1&
1%
b101 $
b101 3
b101 6
b10 #
b10 2
b10 9
b101 "
b101 1
b101 <
b0 =
b11 *
b11 5
b11 >
b11 )
b11 8
b11 @
b11 (
b11 ;
b11 B
1!
#430
0&
0%
b0 $
b0 3
b0 6
b0 #
b0 2
b0 9
b0 "
b0 1
b0 <
0?
b0 *
b0 5
b0 >
0A
b0 )
b0 8
b0 @
0C
b0 (
b0 ;
b0 B
0!
#435
b1 =
1!
#440
0!
#445
b10 =
1!
#450
0!
#455
b11 =
1!
#460
0!
#465
0'
b100 =
1!
#470
b1 $
b1 3
b1 6
b1 "
b1 1
b1 <
b1 *
b1 5
b1 >
b1 )
b1 8
b1 @
b1 (
b1 ;
b1 B
1?
1A
1C
0!
#475
b11 $
b11 3
b11 6
b1 #
b1 2
b1 9
b11 "
b11 1
b11 <
b101 =
b10 *
b10 5
b10 >
b10 )
b10 8
b10 @
b10 (
b10 ;
b10 B
1!
#480
0!
#485
1'
1&
1%
b101 $
b101 3
b101 6
b10 #
b10 2
b10 9
b101 "
b101 1
b101 <
b0 =
b11 *
b11 5
b11 >
b11 )
b11 8
b11 @
b11 (
b11 ;
b11 B
1!
#490
0&
0%
b0 $
b0 3
b0 6
b0 #
b0 2
b0 9
b0 "
b0 1
b0 <
0?
b0 *
b0 5
b0 >
0A
b0 )
b0 8
b0 @
0C
b0 (
b0 ;
b0 B
0!
#495
b1 =
1!
#500
0!
#505
b10 =
1!
#510
0!
#515
b11 =
1!
#520
0!
#525
0'
b100 =
1!
#530
b1 $
b1 3
b1 6
b1 "
b1 1
b1 <
b1 *
b1 5
b1 >
b1 )
b1 8
b1 @
b1 (
b1 ;
b1 B
1?
1A
1C
0!
#535
b11 $
b11 3
b11 6
b1 #
b1 2
b1 9
b11 "
b11 1
b11 <
b101 =
b10 *
b10 5
b10 >
b10 )
b10 8
b10 @
b10 (
b10 ;
b10 B
1!
#540
0!
#545
1'
1&
1%
b101 $
b101 3
b101 6
b10 #
b10 2
b10 9
b101 "
b101 1
b101 <
b0 =
b11 *
b11 5
b11 >
b11 )
b11 8
b11 @
b11 (
b11 ;
b11 B
1!
#550
0&
0%
b0 $
b0 3
b0 6
b0 #
b0 2
b0 9
b0 "
b0 1
b0 <
0?
b0 *
b0 5
b0 >
0A
b0 )
b0 8
b0 @
0C
b0 (
b0 ;
b0 B
0!
#555
b1 =
1!
#560
0!
#565
b10 =
1!
#570
0!
#575
b11 =
1!
#580
0!
#585
0'
b100 =
1!
#590
b1 $
b1 3
b1 6
b1 "
b1 1
b1 <
b1 *
b1 5
b1 >
b1 )
b1 8
b1 @
b1 (
b1 ;
b1 B
1?
1A
1C
0!
#595
b11 $
b11 3
b11 6
b1 #
b1 2
b1 9
b11 "
b11 1
b11 <
b101 =
b10 *
b10 5
b10 >
b10 )
b10 8
b10 @
b10 (
b10 ;
b10 B
1!
#600
0!
#605
1'
1&
1%
b101 $
b101 3
b101 6
b10 #
b10 2
b10 9
b101 "
b101 1
b101 <
b0 =
b11 *
b11 5
b11 >
b11 )
b11 8
b11 @
b11 (
b11 ;
b11 B
1!
#610
0&
0%
b0 $
b0 3
b0 6
b0 #
b0 2
b0 9
b0 "
b0 1
b0 <
0?
b0 *
b0 5
b0 >
0A
b0 )
b0 8
b0 @
0C
b0 (
b0 ;
b0 B
0!
#615
b1 =
1!
#620
0!
#625
b10 =
1!
#630
0!
#635
b11 =
1!
#640
0!
#645
0'
b100 =
1!
#650
b1 $
b1 3
b1 6
b1 "
b1 1
b1 <
b1 *
b1 5
b1 >
b1 )
b1 8
b1 @
b1 (
b1 ;
b1 B
1?
1A
1C
0!
#655
b11 $
b11 3
b11 6
b1 #
b1 2
b1 9
b11 "
b11 1
b11 <
b101 =
b10 *
b10 5
b10 >
b10 )
b10 8
b10 @
b10 (
b10 ;
b10 B
1!
#660
0!
#665
1'
1&
1%
b101 $
b101 3
b101 6
b10 #
b10 2
b10 9
b101 "
b101 1
b101 <
b0 =
b11 *
b11 5
b11 >
b11 )
b11 8
b11 @
b11 (
b11 ;
b11 B
1!
#670
0&
0%
b0 $
b0 3
b0 6
b0 #
b0 2
b0 9
b0 "
b0 1
b0 <
0?
b0 *
b0 5
b0 >
0A
b0 )
b0 8
b0 @
0C
b0 (
b0 ;
b0 B
0!
#675
b1 =
1!
#680
0!
#685
b10 =
1!
#690
0!
#695
b11 =
1!
#700
0!
#705
0'
b100 =
1!
#710
b1 $
b1 3
b1 6
b1 "
b1 1
b1 <
b1 *
b1 5
b1 >
b1 )
b1 8
b1 @
b1 (
b1 ;
b1 B
1?
1A
1C
0!
#715
b11 $
b11 3
b11 6
b1 #
b1 2
b1 9
b11 "
b11 1
b11 <
b101 =
b10 *
b10 5
b10 >
b10 )
b10 8
b10 @
b10 (
b10 ;
b10 B
1!
#720
0!
#725
1'
1&
1%
b101 $
b101 3
b101 6
b10 #
b10 2
b10 9
b101 "
b101 1
b101 <
b0 =
b11 *
b11 5
b11 >
b11 )
b11 8
b11 @
b11 (
b11 ;
b11 B
1!
#730
0&
0%
b0 $
b0 3
b0 6
b0 #
b0 2
b0 9
b0 "
b0 1
b0 <
0?
b0 *
b0 5
b0 >
0A
b0 )
b0 8
b0 @
0C
b0 (
b0 ;
b0 B
0!
#735
b1 =
1!
#740
0!
#745
b10 =
1!
#750
0!
#755
b11 =
1!
#760
0!
#765
0'
b100 =
1!
#770
b1 $
b1 3
b1 6
b1 "
b1 1
b1 <
b1 *
b1 5
b1 >
b1 )
b1 8
b1 @
b1 (
b1 ;
b1 B
1?
1A
1C
0!
#775
b11 $
b11 3
b11 6
b1 #
b1 2
b1 9
b11 "
b11 1
b11 <
b101 =
b10 *
b10 5
b10 >
b10 )
b10 8
b10 @
b10 (
b10 ;
b10 B
1!
#780
0!
#785
1'
1&
1%
b101 $
b101 3
b101 6
b10 #
b10 2
b10 9
b101 "
b101 1
b101 <
b0 =
b11 *
b11 5
b11 >
b11 )
b11 8
b11 @
b11 (
b11 ;
b11 B
1!
#790
0&
0%
b0 $
b0 3
b0 6
b0 #
b0 2
b0 9
b0 "
b0 1
b0 <
0?
b0 *
b0 5
b0 >
0A
b0 )
b0 8
b0 @
0C
b0 (
b0 ;
b0 B
0!
#795
b1 =
1!
